lazy_dataset/__init__.py
lazy_dataset/core.py
lazy_dataset/database.py
lazy_dataset/database_cli.py
lazy_dataset/parallel_utils.py
lazy_dataset-0.0.15.dist-info/LICENSE
lazy_dataset-0.0.15.dist-info/METADATA
lazy_dataset-0.0.15.dist-info/WHEEL
lazy_dataset-0.0.15.dist-info/top_level.txt
lazy_dataset-0.0.15.dist-info/RECORD
