Metadata-Version: 2.1
Name: lazy-dataset
Version: 0.0.15
Summary: Process large datasets as if it was an iterable.
Home-page: https://github.com/fgnt/lazy_dataset
Author: Christoph Boeddeker
Author-email: boeddeker@nt.upb.de
License: MIT
Classifier: License :: OSI Approved :: MIT License
Classifier: Programming Language :: Python
Classifier: Programming Language :: Python :: 3
Classifier: Programming Language :: Python :: 3.6
Classifier: Programming Language :: Python :: Implementation :: CPython
Classifier: Programming Language :: Python :: Implementation :: PyPy
Requires-Python: >=3.6.0
License-File: LICENSE
Requires-Dist: numpy
Provides-Extra: all
Requires-Dist: pathos ; extra == 'all'
Requires-Dist: paderbox ; extra == 'all'
Requires-Dist: psutil ; extra == 'all'
Requires-Dist: diskcache ; extra == 'all'
Requires-Dist: dill ; extra == 'all'
Requires-Dist: humanfriendly ; extra == 'all'
Requires-Dist: mock ; extra == 'all'
Requires-Dist: IPython <8.0 ; (python_version == "3.7") and extra == 'all'
Requires-Dist: IPython <8.13.0 ; (python_version == "3.8") and extra == 'all'
Requires-Dist: IPython ; (python_version >= "3.9") and extra == 'all'
Provides-Extra: cache
Requires-Dist: humanfriendly ; extra == 'cache'
Requires-Dist: psutil ; extra == 'cache'
Requires-Dist: diskcache ; extra == 'cache'
Provides-Extra: cli
Requires-Dist: paderbox ; extra == 'cli'
Requires-Dist: IPython <8.0 ; (python_version == "3.7") and extra == 'cli'
Requires-Dist: IPython <8.13.0 ; (python_version == "3.8") and extra == 'cli'
Requires-Dist: IPython ; (python_version >= "3.9") and extra == 'cli'
Provides-Extra: test
Requires-Dist: paderbox ; extra == 'test'
Requires-Dist: mock ; extra == 'test'
Requires-Dist: dill ; extra == 'test'
Requires-Dist: pathos ; extra == 'test'
